knikkersorteermachine/__init__.py
knikkersorteermachine-1.0.0.dist-info/LICENSE
knikkersorteermachine-1.0.0.dist-info/METADATA
knikkersorteermachine-1.0.0.dist-info/WHEEL
knikkersorteermachine-1.0.0.dist-info/top_level.txt
knikkersorteermachine-1.0.0.dist-info/RECORD
